LICENSE.txt
README.md
bf_nlu_banki/__init__.py
bf_nlu_banki/__main__.py
bf_nlu_banki/api.py
bf_nlu_banki/cli/__init__.py
bf_nlu_banki/cli/arguments/__init__.py
bf_nlu_banki/cli/arguments/data.py
bf_nlu_banki/cli/arguments/default_arguments.py
bf_nlu_banki/cli/arguments/evaluate.py
bf_nlu_banki/cli/arguments/export.py
bf_nlu_banki/cli/arguments/interactive.py
bf_nlu_banki/cli/arguments/run.py
bf_nlu_banki/cli/arguments/shell.py
bf_nlu_banki/cli/arguments/test.py
bf_nlu_banki/cli/arguments/train.py
bf_nlu_banki/cli/arguments/visualize.py
bf_nlu_banki/cli/arguments/x.py
bf_nlu_banki/cli/data.py
bf_nlu_banki/cli/evaluate.py
bf_nlu_banki/cli/export.py
bf_nlu_banki/cli/initial_project/actions/__init__.py
bf_nlu_banki/cli/initial_project/actions/actions.py
bf_nlu_banki/cli/initial_project/config.yml
bf_nlu_banki/cli/initial_project/credentials.yml
bf_nlu_banki/cli/initial_project/data/nlu.yml
bf_nlu_banki/cli/initial_project/data/rules.yml
bf_nlu_banki/cli/initial_project/data/stories.yml
bf_nlu_banki/cli/initial_project/domain.yml
bf_nlu_banki/cli/initial_project/endpoints.yml
bf_nlu_banki/cli/initial_project/tests/test_stories.yml
bf_nlu_banki/cli/interactive.py
bf_nlu_banki/cli/run.py
bf_nlu_banki/cli/scaffold.py
bf_nlu_banki/cli/shell.py
bf_nlu_banki/cli/telemetry.py
bf_nlu_banki/cli/test.py
bf_nlu_banki/cli/train.py
bf_nlu_banki/cli/utils.py
bf_nlu_banki/cli/visualize.py
bf_nlu_banki/cli/x.py
bf_nlu_banki/constants.py
bf_nlu_banki/core/__init__.py
bf_nlu_banki/core/actions/__init__.py
bf_nlu_banki/core/actions/action.py
bf_nlu_banki/core/actions/forms.py
bf_nlu_banki/core/actions/loops.py
bf_nlu_banki/core/actions/two_stage_fallback.py
bf_nlu_banki/core/agent.py
bf_nlu_banki/core/brokers/__init__.py
bf_nlu_banki/core/brokers/broker.py
bf_nlu_banki/core/brokers/file.py
bf_nlu_banki/core/brokers/kafka.py
bf_nlu_banki/core/brokers/pika.py
bf_nlu_banki/core/brokers/sql.py
bf_nlu_banki/core/channels/__init__.py
bf_nlu_banki/core/channels/bf_nlu_banki_chat.py
bf_nlu_banki-1.4.dist-info/entry_points.txt
bf_nlu_banki-1.4.dist-info/LICENSE.txt
bf_nlu_banki-1.4.dist-info/WHEEL
bf_nlu_banki-1.4.dist-info/METADATA
bf_nlu_banki-1.4.dist-info/RECORD
