Metadata-Version: 2.1
Name: bf-nlu-banki
Version: 1.4
Summary: 
License: Apache-2.0
Keywords: nlp,machine-learning,machine-learning-library,bot,bots,botkit,bf_nlu_banki conversational-agents,conversational-ai,chatbot,chatbot-framework,bot-framework
Author: botsfactory
Maintainer: botsfactory
Requires-Python: >=3.7,<3.10
Classifier: Development Status :: 5 - Production/Stable
Classifier: Intended Audience :: Developers
Classifier: License :: OSI Approved :: Apache Software License
Classifier: Programming Language :: Python :: 3
Classifier: Programming Language :: Python :: 3.7
Classifier: Programming Language :: Python :: 3.8
Classifier: Programming Language :: Python :: 3.9
Classifier: Topic :: Software Development :: Libraries
Provides-Extra: full
Provides-Extra: gh-release-notes
Provides-Extra: jieba
Provides-Extra: spacy
Provides-Extra: transformers
Requires-Dist: CacheControl (>=0.12.9,<0.13.0)
Requires-Dist: PyJWT[crypto] (>=2.0.0,<3.0.0)
Requires-Dist: SQLAlchemy (>=1.4.0,<1.5.0)
Requires-Dist: absl-py (>=0.9,<0.14)
Requires-Dist: aio-pika (>=6.7.1,<7.0.0)
Requires-Dist: aiohttp (>=3.6,<3.8,!=3.7.4.post0)
Requires-Dist: apscheduler (>=3.6,<3.8)
Requires-Dist: arabic_reshaper (>=2.1.3,<3.0.0)
Requires-Dist: attrs (>=19.3,<21.3)
Requires-Dist: boto3 (>=1.12,<2.0)
Requires-Dist: cloudpickle (>=1.2,<1.7)
Requires-Dist: colorama (>=0.4.4,<0.5.0); sys_platform == "win32"
Requires-Dist: colorclass (>=2.2,<2.3)
Requires-Dist: coloredlogs (>=10,<16)
Requires-Dist: colorhash (>=1.0.2,<1.1.0)
Requires-Dist: dask (==2021.11.2)
Requires-Dist: datefinder (>=0.7.1,<0.8.0)
Requires-Dist: fbmessenger (>=6.0.0,<6.1.0)
Requires-Dist: github3.py (>=1.3.0,<1.4.0); extra == "gh-release-notes"
Requires-Dist: google-auth (<2)
Requires-Dist: jellyfish (>=0.9.0,<0.10.0)
Requires-Dist: jieba (>=0.39,<0.43); extra == "jieba" or extra == "full"
Requires-Dist: joblib (>=0.15.1,<1.1.0)
Requires-Dist: jsonpickle (>=1.3,<2.1)
Requires-Dist: jsonschema (>=3.2,<4.5)
Requires-Dist: kafka-python (>=1.4,<3.0)
Requires-Dist: matplotlib (>=3.1,<3.4)
Requires-Dist: mattermostwrapper (>=2.2,<2.3)
Requires-Dist: networkx (>=2.4,<2.7)
Requires-Dist: numpy (>=1.19.2,<1.20.0)
Requires-Dist: packaging (>=20.0,<21.0)
Requires-Dist: prompt-toolkit (>=2.0,<3.0)
Requires-Dist: psycopg2-binary (>=2.8.2,<2.10.0)
Requires-Dist: pyTelegramBotAPI (>=3.7.3,<4.0.0)
Requires-Dist: pyarabic (>=0.6.14,<0.7.0)
Requires-Dist: pydot (>=1.4,<1.5)
Requires-Dist: pykwalify (>=1.7,<1.9)
Requires-Dist: pymongo[srv,tls] (>=3.8,<3.11)
Requires-Dist: python-dateutil (>=2.8,<2.9)
Requires-Dist: python-engineio (>=4,<6,!=5.0.0)
Requires-Dist: python-socketio (>=4.4,<6)
Requires-Dist: pytz (>=2019.1,<2022.0)
Requires-Dist: questionary (>=1.5.1,<1.11.0)
Requires-Dist: randomname (>=0.1.5,<0.2.0)
Requires-Dist: rasa-sdk (>=3.1.1,<3.2.0)
Requires-Dist: redis (>=3.4,<4.0)
Requires-Dist: regex (>=2020.6,<2022.5)
Requires-Dist: requests (>=2.23,<3.0)
Requires-Dist: rocketchat_API (>=0.6.31,<1.26.0)
Requires-Dist: ruamel.yaml (>=0.16.5,<0.17.0)
Requires-Dist: sanic (>=21.12,<21.13)
Requires-Dist: sanic-cors (>=2.0.0,<3.0.0)
Requires-Dist: sanic-jwt (>=1.6.0,<2.0.0)
Requires-Dist: sanic-routing (>=0.7.2,<0.8.0)
Requires-Dist: scikit-learn (>=0.22,<0.25)
Requires-Dist: scipy (>=1.4.1,<2.0.0)
Requires-Dist: sentencepiece[sentencepiece] (>=0.1.96,<0.2.0); extra == "transformers" or extra == "full"
Requires-Dist: sentry-sdk (>=0.17.0,<1.4.0)
Requires-Dist: setuptools (>=41.0.0)
Requires-Dist: sklearn-crfsuite (>=0.3,<0.4)
Requires-Dist: slackclient (>=2.0.0,<3.0.0)
Requires-Dist: spacy (>=3.1,<4.0); extra == "spacy" or extra == "full"
Requires-Dist: tarsafe (>=0.0.3,<0.0.4)
Requires-Dist: tensorflow (>=2.7.0,<2.8.0)
Requires-Dist: tensorflow-addons (>=0.15.0,<0.16.0)
Requires-Dist: tensorflow-text (>=2.7.0,<3.0.0); sys_platform != "win32"
Requires-Dist: tensorflow_hub (>=0.12.0,<0.13.0)
Requires-Dist: terminaltables (>=3.1.0,<3.2.0)
Requires-Dist: tqdm (>=4.31,<5.0)
Requires-Dist: transformers (>=4.13.0,<4.14.0); extra == "transformers" or extra == "full"
Requires-Dist: twilio (>=6.26,<6.51)
Requires-Dist: typing-extensions (>=3.7.4,<4.0.0)
Requires-Dist: typing-utils (>=0.1.0,<0.2.0)
Requires-Dist: ujson (>=1.35,<6.0)
Requires-Dist: webexteamssdk (>=1.1.1,<1.7.0)
